deeputil/__init__.py
deeputil/keep_running.py
deeputil/misc.py
deeputil/priority_dict.py
deeputil/streamcounter.py
deeputil/timer.py
deeputil-0.2.10.dist-info/LICENSE
deeputil-0.2.10.dist-info/METADATA
deeputil-0.2.10.dist-info/WHEEL
deeputil-0.2.10.dist-info/dependency_links.txt
deeputil-0.2.10.dist-info/top_level.txt
deeputil-0.2.10.dist-info/RECORD
