Metadata-Version: 2.1
Name: deeputil
Version: 0.2.10
Summary: Commonly re-used logic kept in one library
Home-page: https://github.com/deep-compute/deeputil
Author: Deep Compute, LLC
Author-email: contact@deepcompute.com
License: MIT
Keywords: deeputil
Platform: UNKNOWN
Classifier: Programming Language :: Python :: 3.5
Classifier: Programming Language :: Python :: 2.7
Classifier: Environment :: Console
Classifier: Intended Audience :: Developers
Classifier: License :: OSI Approved :: MIT License
Requires-Dist: repoze.lru
Requires-Dist: six
